bullmq/__init__.py
bullmq/backoffs.py
bullmq/error_code.py
bullmq/event_emitter.py
bullmq/flow_producer.py
bullmq/job.py
bullmq/queue.py
bullmq/queue_keys.py
bullmq/redis_connection.py
bullmq/scripts.py
bullmq/timer.py
bullmq/utils.py
bullmq/worker.py
bullmq/commands/addDelayedJob-6.lua
bullmq/commands/addJobScheduler-11.lua
bullmq/commands/addLog-2.lua
bullmq/commands/addParentJob-6.lua
bullmq/commands/addPrioritizedJob-9.lua
bullmq/commands/addRepeatableJob-2.lua
bullmq/commands/addStandardJob-9.lua
bullmq/commands/changeDelay-4.lua
bullmq/commands/changePriority-7.lua
bullmq/commands/cleanJobsInSet-3.lua
bullmq/commands/drain-5.lua
bullmq/commands/extendLock-2.lua
bullmq/commands/extendLocks-1.lua
bullmq/commands/getCounts-1.lua
bullmq/commands/getCountsPerPriority-4.lua
bullmq/commands/getDependencyCounts-4.lua
bullmq/commands/getJobScheduler-1.lua
bullmq/commands/getMetrics-2.lua
bullmq/commands/getRanges-1.lua
bullmq/commands/getRateLimitTtl-2.lua
bullmq/commands/getState-8.lua
bullmq/commands/getStateV2-8.lua
bullmq/commands/isFinished-3.lua
bullmq/commands/isJobInList-1.lua
bullmq/commands/isMaxed-2.lua
bullmq/commands/moveJobFromActiveToWait-9.lua
bullmq/commands/moveJobsToWait-8.lua
bullmq/commands/moveStalledJobsToWait-8.lua
bullmq/commands/moveToActive-11.lua
bullmq/commands/moveToDelayed-8.lua
bullmq/commands/moveToFinished-14.lua
bullmq/commands/moveToWaitingChildren-7.lua
bullmq/commands/obliterate-2.lua
bullmq/commands/paginate-1.lua
bullmq/commands/pause-7.lua
bullmq/commands/promote-9.lua
bullmq/commands/releaseLock-1.lua
bullmq/commands/removeChildDependency-1.lua
bullmq/commands/removeDeduplicationKey-1.lua
bullmq/commands/removeJob-2.lua
bullmq/commands/removeJobScheduler-3.lua
bullmq/commands/removeRepeatable-3.lua
bullmq/commands/removeUnprocessedChildren-2.lua
bullmq/commands/reprocessJob-8.lua
bullmq/commands/retryJob-11.lua
bullmq/commands/saveStacktrace-1.lua
bullmq/commands/updateData-1.lua
bullmq/commands/updateJobScheduler-12.lua
bullmq-2.18.3.dist-info/METADATA
bullmq-2.18.3.dist-info/WHEEL
bullmq-2.18.3.dist-info/top_level.txt
bullmq-2.18.3.dist-info/RECORD
