Metadata-Version: 2.4
Name: bullmq
Version: 2.18.3
Summary: BullMQ for Python
Author-email: "Taskforce.sh Inc." <manast@taskforce.sh>
Project-URL: Homepage, https://bullmq.io
Project-URL: Bug Tracker, https://github.com/taskforcesh/bullmq/issues
Keywords: python,bullmq,queues
Classifier: Development Status :: 3 - Alpha
Classifier: Intended Audience :: Developers
Classifier: License :: OSI Approved :: MIT License
Classifier: Operating System :: POSIX :: Linux
Classifier: Programming Language :: Python :: 3.10
Requires-Python: >=3.10.0
Requires-Dist: redis==6.4.0
Requires-Dist: msgpack==1.1.2
Requires-Dist: semver==3.0.4
Provides-Extra: dev
Requires-Dist: pre-commit==3.3.3; extra == "dev"
Requires-Dist: build==0.8.0; extra == "dev"
Requires-Dist: types-redis==4.6.0.2; extra == "dev"
